blockcontent/__init__.py
blockcontent/api_client.py
blockcontent/api_response.py
blockcontent/configuration.py
blockcontent/exceptions.py
blockcontent/py.typed
blockcontent/rest.py
blockcontent/api/__init__.py
blockcontent/models/__init__.py
blockcontent/models/block.py
blockcontent/models/chart_content.py
blockcontent/models/chart_content_datasets_inner.py
blockcontent/models/code_content.py
blockcontent/models/table_content.py
blockcontent/models/text_content.py
blockcontent-0.2.0.dist-info/METADATA
blockcontent-0.2.0.dist-info/WHEEL
blockcontent-0.2.0.dist-info/top_level.txt
blockcontent-0.2.0.dist-info/RECORD
